mkignore/__init__.py
mkignore/console_script.py
mkignore-0.1.5.dist-info/LICENSE
mkignore-0.1.5.dist-info/METADATA
mkignore-0.1.5.dist-info/WHEEL
mkignore-0.1.5.dist-info/entry_points.txt
mkignore-0.1.5.dist-info/top_level.txt
mkignore-0.1.5.dist-info/RECORD
