Metadata-Version: 2.1
Name: mkignore
Version: 0.1.5
Summary: Generate .gitignore files from templates
Home-page: https://github.com/EClaesson/mkignore
Author: Emanuel Claesson
Author-email: emanuel.claesson@gmail.com
License: UNKNOWN
Platform: UNKNOWN
Classifier: Programming Language :: Python :: 3
Classifier: License :: OSI Approved :: MIT License
Classifier: Operating System :: OS Independent
Requires-Python: >=3.5
Requires-Dist: dload (>=0.6)
